progres/__init__.py
progres/progres.py
progres/chainsaw/__init__.py
progres/chainsaw/get_predictions.py
progres/chainsaw/src/__init__.py
progres/chainsaw/src/constants.py
progres/chainsaw/src/domain_chop.py
progres/chainsaw/src/errors.py
progres/chainsaw/src/factories.py
progres/chainsaw/src/featurisers.py
progres/chainsaw/src/loggers.py
progres/chainsaw/src/domain_assignment/__init__.py
progres/chainsaw/src/domain_assignment/assigners.py
progres/chainsaw/src/domain_assignment/sparse_lowrank.py
progres/chainsaw/src/domain_assignment/util.py
progres/chainsaw/src/models/__init__.py
progres/chainsaw/src/models/results.py
progres/chainsaw/src/models/rosetta.py
progres/chainsaw/src/utils/__init__.py
progres/chainsaw/src/utils/cif2pdb.py
progres/chainsaw/src/utils/common.py
progres/chainsaw/src/utils/domain_boundary_distance_score.py
progres/chainsaw/src/utils/ndo_score.py
progres/chainsaw/src/utils/pdb_reres.py
progres/chainsaw/src/utils/secondary_structure.py
progres-1.1.0.data/scripts/progres
progres-1.1.0.dist-info/licenses/LICENSE
progres-1.1.0.dist-info/METADATA
progres-1.1.0.dist-info/WHEEL
progres-1.1.0.dist-info/top_level.txt
progres-1.1.0.dist-info/RECORD
