Metadata-Version: 2.4
Name: progres
Version: 1.1.0
Summary: Fast protein structure searching using structure graph embeddings
Home-page: https://github.com/greener-group/progres
Author: Joe G Greener
Author-email: jgreener@mrc-lmb.cam.ac.uk
License: MIT
Keywords: protein structure search graph embedding
Classifier: Programming Language :: Python :: 3
Classifier: License :: OSI Approved :: MIT License
Classifier: Operating System :: OS Independent
Classifier: Topic :: Scientific/Engineering :: Bio-Informatics
License-File: LICENSE
Requires-Dist: biopython
Requires-Dist: mmtf-python
Requires-Dist: einops
Requires-Dist: pydantic
Dynamic: author
Dynamic: author-email
Dynamic: classifier
Dynamic: description
Dynamic: description-content-type
Dynamic: home-page
Dynamic: keywords
Dynamic: license
Dynamic: license-file
Dynamic: requires-dist
Dynamic: summary
